poppygen/__init__.py
poppygen/person.py
poppygen/population_generator.py
poppygen/datasets/__init__.py
poppygen/datasets/process_acs.py
poppygen/datasets/process_pums.py
poppygen/datasets/process_safegraph_poi.py
poppygen/datasets/data/cbg_b01.csv
poppygen/datasets/data/cbg_field_descriptions.csv
poppygen-0.2.0.dist-info/LICENSE
poppygen-0.2.0.dist-info/METADATA
poppygen-0.2.0.dist-info/WHEEL
poppygen-0.2.0.dist-info/top_level.txt
poppygen-0.2.0.dist-info/RECORD
