Metadata-Version: 2.1
Name: poppygen
Version: 0.2.0
Summary: PopPyGen: Synthetic Human Population Generator for Python
Home-page: https://github.com/tljstewart/poppygen
Author: Timothy L.J. Stewart
Author-email: me@tljstewart.ai
License: BSD-4
Keywords: synthetic population,,human population,demographic
Platform: UNKNOWN
Classifier: Programming Language :: Python :: 3
Classifier: License :: OSI Approved :: BSD License
Classifier: Operating System :: OS Independent
Requires-Python: >=3.9
License-File: LICENSE
Requires-Dist: pandas (==1.3.4)
Requires-Dist: scipy (==1.7.1)
